<?xml version="1.0" encoding="WINDOWS-1252"?>
<!-- Generated by Oracle Reports version 10.1.2.0.2 -->
<IPC_RPT_0173>
  <LIST_G_CASH_RECEIPT_ID>
    <G_CASH_RECEIPT_ID>
      <APPLIED_COUNT>1</APPLIED_COUNT>
      <TAX_R_ALL></TAX_R_ALL>
      <ADDRESS_ALL>A. SORIANO AVENUE, NORTH RECLAMATION AREA, CEBU CITY </ADDRESS_ALL>
      <BUSINESS_STYLE>MOTOR VEHICLES, RETAILING</BUSINESS_STYLE>
      <RECEIPT_AMOUNT>1675029.64</RECEIPT_AMOUNT>
      <CURR>PHP</CURR>
      <REFERENCE></REFERENCE>
      <B_AMOUNT>290371</B_AMOUNT>
      <BANK>sb</BANK>
      <RECEIPT_NUM>000000439</RECEIPT_NUM>
      <DATE2>Oct 26, 2017</DATE2>
      <COMMENTS></COMMENTS>
      <CASH_RECEIPT_ID>326108</CASH_RECEIPT_ID>
      <RECEIPT_NUMBER>70100013151</RECEIPT_NUMBER>
      <date1>10-26-17</date1>
      <PAY_FROM_CUSTOMER>15141</PAY_FROM_CUSTOMER>
      <CUSTOMER_SITE_USE_ID>20527</CUSTOMER_SITE_USE_ID>
      <AMOUNT123>1675029.64</AMOUNT123>
      <LIST_G_TRX_NUMBER>
        <G_TRX_NUMBER>
          <WHT_TAX>15191.07</WHT_TAX>
          <BALANCE_PAYABLE>11179.29</BALANCE_PAYABLE>
          <AMOUNT_APPLIED>1675029.64</AMOUNT_APPLIED>
          <TAX_REFERENCE>005-104-972-000</TAX_REFERENCE>
          <CUSTOMER_TRX_ID>999907</CUSTOMER_TRX_ID>
          <CASH_RECEIPT_ID1>326108</CASH_RECEIPT_ID1>
          <TRX_NUMBER>40300017986</TRX_NUMBER>
          <INVOICE_AMOUNT>1701400</INVOICE_AMOUNT>
          <DESC1>170UCS5YGWLNADP 4X4 AT LS-A SILKY PEARL WHITE</DESC1>
          <CF_LINE_AMOUNT>1701400</CF_LINE_AMOUNT>
          <ADJUST>0</ADJUST>
          <CS_COUNT>1</CS_COUNT>
        </G_TRX_NUMBER>
      </LIST_G_TRX_NUMBER>
      <CS_AMT_APPLIED>1675029.64</CS_AMT_APPLIED>
      <DFF_RECEIPT>290371</DFF_RECEIPT>
      <AMOUNT>1701400</AMOUNT>
      <CUST_NAME>ISUZU CEBU INC.</CUST_NAME>
      <CUST_TIN></CUST_TIN>
      <CUST_ADD>A. SORIANO AVENUE, NORTH RECLAMATION AREA, CEBU CITY</CUST_ADD>
      <EWT_AMT>26370.36</EWT_AMT>
      <AMT_WORD>One Million Six Hundred Seventy-Five Thousand Twenty-Nine &amp; 64/100</AMT_WORD>
      <TAX_APPLIED>182292.86</TAX_APPLIED>
      <INV_REF>40300017986</INV_REF>
      <LINE_APPLIED>1519107.14</LINE_APPLIED>
      <TOTAL1>1701400</TOTAL1>
      <CF_ADV_AMOUNT>0</CF_ADV_AMOUNT>
      <OU_TIN>004-834-871-000</OU_TIN>
      <CF_SUB_TOTAL>1701400</CF_SUB_TOTAL>
      <CS_TOTAL_ADJUST>0</CS_TOTAL_ADJUST>
      <CF_TOTAL_ADJUST>0</CF_TOTAL_ADJUST>
      <CF_ISSUE2> </CF_ISSUE2>
      <CF_BIR2> </CF_BIR2>
      <CS_TOTAL_LINE_AMOUNT>1701400</CS_TOTAL_LINE_AMOUNT>
    </G_CASH_RECEIPT_ID>
  </LIST_G_CASH_RECEIPT_ID>
  <LEDGER_NAME>IPC</LEDGER_NAME>
  <TIN1>004-834-871-000</TIN1>
  <ADD1>114 Technology Avenue, Phase 11, Laguna Technopark,,,Biñan, Laguna,PH</ADD1>
  <CF_BIR> </CF_BIR>
  <CF_ISSUE> </CF_ISSUE>
</IPC_RPT_0173>
