<?xml version="1.0" encoding="WINDOWS-1252"?>
<!-- Generated by Oracle Reports version 10.1.2.0.2 -->
<IPC_RPT_2166>
  <LIST_G_RECEIPT_NUMBER>
    <G_RECEIPT_NUMBER>
      <RECEIPT_NUMBER>070420</RECEIPT_NUMBER>
      <DOC_SEQUENCE_VALUE>70100007880</DOC_SEQUENCE_VALUE>
      <CUSTOMER_NAME>HOUSE OF INVESTMENTS, INCORPORATED</CUSTOMER_NAME>
      <ACCOUNT_NUMBER>1746</ACCOUNT_NUMBER>
      <ACCOUNT_NAME>COMMONWEALTH</ACCOUNT_NAME>
      <LOCATION>DEALERS-VEHICLE</LOCATION>
      <CURRENCY_CODE>PHP</CURRENCY_CODE>
      <UNIDENTIFIED_AMOUNT>0</UNIDENTIFIED_AMOUNT>
      <UNAPPLIED_AMOUNT>264259.29</UNAPPLIED_AMOUNT>
      <APPLIED_AMOUNT>1355329.82</APPLIED_AMOUNT>
      <RECEIPT_AMOUNT>1619589.11</RECEIPT_AMOUNT>
      <RECEIPT_DATE>04-JUL-17</RECEIPT_DATE>
      <STATUS>Unapplied</STATUS>
    </G_RECEIPT_NUMBER>
    <G_RECEIPT_NUMBER>
      <RECEIPT_NUMBER>071129</RECEIPT_NUMBER>
      <DOC_SEQUENCE_VALUE>70100008185</DOC_SEQUENCE_VALUE>
      <CUSTOMER_NAME></CUSTOMER_NAME>
      <ACCOUNT_NUMBER></ACCOUNT_NUMBER>
      <ACCOUNT_NAME></ACCOUNT_NAME>
      <LOCATION></LOCATION>
      <CURRENCY_CODE>PHP</CURRENCY_CODE>
      <UNIDENTIFIED_AMOUNT>1600</UNIDENTIFIED_AMOUNT>
      <UNAPPLIED_AMOUNT></UNAPPLIED_AMOUNT>
      <APPLIED_AMOUNT></APPLIED_AMOUNT>
      <RECEIPT_AMOUNT>1600</RECEIPT_AMOUNT>
      <RECEIPT_DATE>11-JUL-17</RECEIPT_DATE>
      <STATUS>Unidentified</STATUS>
    </G_RECEIPT_NUMBER>
    <G_RECEIPT_NUMBER>
      <RECEIPT_NUMBER>071462</RECEIPT_NUMBER>
      <DOC_SEQUENCE_VALUE>70100008325</DOC_SEQUENCE_VALUE>
      <CUSTOMER_NAME>ISUZU ILOILO CORPORATION</CUSTOMER_NAME>
      <ACCOUNT_NUMBER>1761</ACCOUNT_NUMBER>
      <ACCOUNT_NAME>ILOILO</ACCOUNT_NAME>
      <LOCATION>DEALERS-VEHICLE</LOCATION>
      <CURRENCY_CODE>PHP</CURRENCY_CODE>
      <UNIDENTIFIED_AMOUNT>0</UNIDENTIFIED_AMOUNT>
      <UNAPPLIED_AMOUNT>16634.64</UNAPPLIED_AMOUNT>
      <APPLIED_AMOUNT>1267120</APPLIED_AMOUNT>
      <RECEIPT_AMOUNT>1283754.64</RECEIPT_AMOUNT>
      <RECEIPT_DATE>14-JUL-17</RECEIPT_DATE>
      <STATUS>Unapplied</STATUS>
    </G_RECEIPT_NUMBER>
    <G_RECEIPT_NUMBER>
      <RECEIPT_NUMBER>048</RECEIPT_NUMBER>
      <DOC_SEQUENCE_VALUE>70100007822</DOC_SEQUENCE_VALUE>
      <CUSTOMER_NAME>INDUSTRIAL &amp;TRANSPORT EQUIPMENT, INC.</CUSTOMER_NAME>
      <ACCOUNT_NUMBER>1754</ACCOUNT_NUMBER>
      <ACCOUNT_NAME>EDSA</ACCOUNT_NAME>
      <LOCATION>DEALERS-VEHICLE</LOCATION>
      <CURRENCY_CODE>PHP</CURRENCY_CODE>
      <UNIDENTIFIED_AMOUNT>0</UNIDENTIFIED_AMOUNT>
      <UNAPPLIED_AMOUNT>809.16</UNAPPLIED_AMOUNT>
      <APPLIED_AMOUNT>838287.86</APPLIED_AMOUNT>
      <RECEIPT_AMOUNT>839097.02</RECEIPT_AMOUNT>
      <RECEIPT_DATE>03-JUL-17</RECEIPT_DATE>
      <STATUS>Unapplied</STATUS>
    </G_RECEIPT_NUMBER>
    <G_RECEIPT_NUMBER>
      <RECEIPT_NUMBER>049</RECEIPT_NUMBER>
      <DOC_SEQUENCE_VALUE>70100007823</DOC_SEQUENCE_VALUE>
      <CUSTOMER_NAME>INDUSTRIAL &amp;TRANSPORT EQUIPMENT, INC.</CUSTOMER_NAME>
      <ACCOUNT_NUMBER>1754</ACCOUNT_NUMBER>
      <ACCOUNT_NAME>EDSA</ACCOUNT_NAME>
      <LOCATION>DEALERS-VEHICLE</LOCATION>
      <CURRENCY_CODE>PHP</CURRENCY_CODE>
      <UNIDENTIFIED_AMOUNT>0</UNIDENTIFIED_AMOUNT>
      <UNAPPLIED_AMOUNT>809.16</UNAPPLIED_AMOUNT>
      <APPLIED_AMOUNT>838287.86</APPLIED_AMOUNT>
      <RECEIPT_AMOUNT>839097.02</RECEIPT_AMOUNT>
      <RECEIPT_DATE>03-JUL-17</RECEIPT_DATE>
      <STATUS>Unapplied</STATUS>
    </G_RECEIPT_NUMBER>
    <G_RECEIPT_NUMBER>
      <RECEIPT_NUMBER>071455</RECEIPT_NUMBER>
      <DOC_SEQUENCE_VALUE>70100008318</DOC_SEQUENCE_VALUE>
      <CUSTOMER_NAME>ISUZU ILOILO CORPORATION</CUSTOMER_NAME>
      <ACCOUNT_NUMBER>1761</ACCOUNT_NUMBER>
      <ACCOUNT_NAME>ILOILO</ACCOUNT_NAME>
      <LOCATION>DEALERS-VEHICLE</LOCATION>
      <CURRENCY_CODE>PHP</CURRENCY_CODE>
      <UNIDENTIFIED_AMOUNT>0</UNIDENTIFIED_AMOUNT>
      <UNAPPLIED_AMOUNT>17744.64</UNAPPLIED_AMOUNT>
      <APPLIED_AMOUNT>1176100</APPLIED_AMOUNT>
      <RECEIPT_AMOUNT>1193844.64</RECEIPT_AMOUNT>
      <RECEIPT_DATE>14-JUL-17</RECEIPT_DATE>
      <STATUS>Unapplied</STATUS>
    </G_RECEIPT_NUMBER>
    <G_RECEIPT_NUMBER>
      <RECEIPT_NUMBER>071128</RECEIPT_NUMBER>
      <DOC_SEQUENCE_VALUE>70100008183</DOC_SEQUENCE_VALUE>
      <CUSTOMER_NAME></CUSTOMER_NAME>
      <ACCOUNT_NUMBER></ACCOUNT_NUMBER>
      <ACCOUNT_NAME></ACCOUNT_NAME>
      <LOCATION></LOCATION>
      <CURRENCY_CODE>PHP</CURRENCY_CODE>
      <UNIDENTIFIED_AMOUNT>1600</UNIDENTIFIED_AMOUNT>
      <UNAPPLIED_AMOUNT></UNAPPLIED_AMOUNT>
      <APPLIED_AMOUNT></APPLIED_AMOUNT>
      <RECEIPT_AMOUNT>1600</RECEIPT_AMOUNT>
      <RECEIPT_DATE>11-JUL-17</RECEIPT_DATE>
      <STATUS>Unidentified</STATUS>
    </G_RECEIPT_NUMBER>
    <G_RECEIPT_NUMBER>
      <RECEIPT_NUMBER>071465</RECEIPT_NUMBER>
      <DOC_SEQUENCE_VALUE>70100008328</DOC_SEQUENCE_VALUE>
      <CUSTOMER_NAME>ISUZU ILOILO CORPORATION</CUSTOMER_NAME>
      <ACCOUNT_NUMBER>1761</ACCOUNT_NUMBER>
      <ACCOUNT_NAME>ILOILO</ACCOUNT_NAME>
      <LOCATION>DEALERS-VEHICLE</LOCATION>
      <CURRENCY_CODE>PHP</CURRENCY_CODE>
      <UNIDENTIFIED_AMOUNT>0</UNIDENTIFIED_AMOUNT>
      <UNAPPLIED_AMOUNT>16634.64</UNAPPLIED_AMOUNT>
      <APPLIED_AMOUNT>1267120</APPLIED_AMOUNT>
      <RECEIPT_AMOUNT>1283754.64</RECEIPT_AMOUNT>
      <RECEIPT_DATE>14-JUL-17</RECEIPT_DATE>
      <STATUS>Unapplied</STATUS>
    </G_RECEIPT_NUMBER>
    <G_RECEIPT_NUMBER>
      <RECEIPT_NUMBER>071466</RECEIPT_NUMBER>
      <DOC_SEQUENCE_VALUE>70100008329</DOC_SEQUENCE_VALUE>
      <CUSTOMER_NAME>ISUZU ILOILO CORPORATION</CUSTOMER_NAME>
      <ACCOUNT_NUMBER>1761</ACCOUNT_NUMBER>
      <ACCOUNT_NAME>ILOILO</ACCOUNT_NAME>
      <LOCATION>DEALERS-VEHICLE</LOCATION>
      <CURRENCY_CODE>PHP</CURRENCY_CODE>
      <UNIDENTIFIED_AMOUNT>0</UNIDENTIFIED_AMOUNT>
      <UNAPPLIED_AMOUNT>16550.71</UNAPPLIED_AMOUNT>
      <APPLIED_AMOUNT>1276520</APPLIED_AMOUNT>
      <RECEIPT_AMOUNT>1293070.71</RECEIPT_AMOUNT>
      <RECEIPT_DATE>14-JUL-17</RECEIPT_DATE>
      <STATUS>Unapplied</STATUS>
    </G_RECEIPT_NUMBER>
    <G_RECEIPT_NUMBER>
      <RECEIPT_NUMBER>070421</RECEIPT_NUMBER>
      <DOC_SEQUENCE_VALUE>70100007881</DOC_SEQUENCE_VALUE>
      <CUSTOMER_NAME>B.M. DOMINGO MOTOR SALES, INC.</CUSTOMER_NAME>
      <ACCOUNT_NUMBER>1725</ACCOUNT_NUMBER>
      <ACCOUNT_NAME>ISABELA</ACCOUNT_NAME>
      <LOCATION>DEALERS-OTHERS</LOCATION>
      <CURRENCY_CODE>PHP</CURRENCY_CODE>
      <UNIDENTIFIED_AMOUNT>0</UNIDENTIFIED_AMOUNT>
      <UNAPPLIED_AMOUNT></UNAPPLIED_AMOUNT>
      <APPLIED_AMOUNT></APPLIED_AMOUNT>
      <RECEIPT_AMOUNT>8604</RECEIPT_AMOUNT>
      <RECEIPT_DATE>04-JUL-17</RECEIPT_DATE>
      <STATUS>Unapplied</STATUS>
    </G_RECEIPT_NUMBER>
    <G_RECEIPT_NUMBER>
      <RECEIPT_NUMBER>071054</RECEIPT_NUMBER>
      <DOC_SEQUENCE_VALUE>70100008156</DOC_SEQUENCE_VALUE>
      <CUSTOMER_NAME>ISUZU ILOILO CORPORATION</CUSTOMER_NAME>
      <ACCOUNT_NUMBER>1761</ACCOUNT_NUMBER>
      <ACCOUNT_NAME>ILOILO</ACCOUNT_NAME>
      <LOCATION>DEALERS-OTHERS</LOCATION>
      <CURRENCY_CODE>PHP</CURRENCY_CODE>
      <UNIDENTIFIED_AMOUNT>0</UNIDENTIFIED_AMOUNT>
      <UNAPPLIED_AMOUNT></UNAPPLIED_AMOUNT>
      <APPLIED_AMOUNT></APPLIED_AMOUNT>
      <RECEIPT_AMOUNT>5899.34</RECEIPT_AMOUNT>
      <RECEIPT_DATE>10-JUL-17</RECEIPT_DATE>
      <STATUS>Unapplied</STATUS>
    </G_RECEIPT_NUMBER>
    <G_RECEIPT_NUMBER>
      <RECEIPT_NUMBER>071461</RECEIPT_NUMBER>
      <DOC_SEQUENCE_VALUE>70100008324</DOC_SEQUENCE_VALUE>
      <CUSTOMER_NAME>ISUZU ILOILO CORPORATION</CUSTOMER_NAME>
      <ACCOUNT_NUMBER>1761</ACCOUNT_NUMBER>
      <ACCOUNT_NAME>ILOILO</ACCOUNT_NAME>
      <LOCATION>DEALERS-VEHICLE</LOCATION>
      <CURRENCY_CODE>PHP</CURRENCY_CODE>
      <UNIDENTIFIED_AMOUNT>0</UNIDENTIFIED_AMOUNT>
      <UNAPPLIED_AMOUNT>16634.64</UNAPPLIED_AMOUNT>
      <APPLIED_AMOUNT>1267120</APPLIED_AMOUNT>
      <RECEIPT_AMOUNT>1283754.64</RECEIPT_AMOUNT>
      <RECEIPT_DATE>14-JUL-17</RECEIPT_DATE>
      <STATUS>Unapplied</STATUS>
    </G_RECEIPT_NUMBER>
    <G_RECEIPT_NUMBER>
      <RECEIPT_NUMBER>071469</RECEIPT_NUMBER>
      <DOC_SEQUENCE_VALUE>70100008333</DOC_SEQUENCE_VALUE>
      <CUSTOMER_NAME>ISUZU ILOILO CORPORATION</CUSTOMER_NAME>
      <ACCOUNT_NUMBER>1761</ACCOUNT_NUMBER>
      <ACCOUNT_NAME>ILOILO</ACCOUNT_NAME>
      <LOCATION>DEALERS-VEHICLE</LOCATION>
      <CURRENCY_CODE>PHP</CURRENCY_CODE>
      <UNIDENTIFIED_AMOUNT>0</UNIDENTIFIED_AMOUNT>
      <UNAPPLIED_AMOUNT>16634.64</UNAPPLIED_AMOUNT>
      <APPLIED_AMOUNT>1267120</APPLIED_AMOUNT>
      <RECEIPT_AMOUNT>1283754.64</RECEIPT_AMOUNT>
      <RECEIPT_DATE>14-JUL-17</RECEIPT_DATE>
      <STATUS>Unapplied</STATUS>
    </G_RECEIPT_NUMBER>
    <G_RECEIPT_NUMBER>
      <RECEIPT_NUMBER>071106</RECEIPT_NUMBER>
      <DOC_SEQUENCE_VALUE>70100008162</DOC_SEQUENCE_VALUE>
      <CUSTOMER_NAME>HOUSE OF INVESTMENTS, INCORPORATED</CUSTOMER_NAME>
      <ACCOUNT_NUMBER>1750</ACCOUNT_NUMBER>
      <ACCOUNT_NAME>MANILA</ACCOUNT_NAME>
      <LOCATION>DEALERS-FLEET</LOCATION>
      <CURRENCY_CODE>PHP</CURRENCY_CODE>
      <UNIDENTIFIED_AMOUNT>0</UNIDENTIFIED_AMOUNT>
      <UNAPPLIED_AMOUNT>421691.96</UNAPPLIED_AMOUNT>
      <APPLIED_AMOUNT>861250</APPLIED_AMOUNT>
      <RECEIPT_AMOUNT>1282941.96</RECEIPT_AMOUNT>
      <RECEIPT_DATE>11-JUL-17</RECEIPT_DATE>
      <STATUS>Unapplied</STATUS>
    </G_RECEIPT_NUMBER>
    <G_RECEIPT_NUMBER>
      <RECEIPT_NUMBER>071117</RECEIPT_NUMBER>
      <DOC_SEQUENCE_VALUE>70100008173</DOC_SEQUENCE_VALUE>
      <CUSTOMER_NAME>ISUZU AUTOMOTIVE DEALERSHIP, INC.</CUSTOMER_NAME>
      <ACCOUNT_NUMBER>1748</ACCOUNT_NUMBER>
      <ACCOUNT_NAME>ALABANG</ACCOUNT_NAME>
      <LOCATION>DEALERS-PARTS</LOCATION>
      <CURRENCY_CODE>PHP</CURRENCY_CODE>
      <UNIDENTIFIED_AMOUNT>0</UNIDENTIFIED_AMOUNT>
      <UNAPPLIED_AMOUNT></UNAPPLIED_AMOUNT>
      <APPLIED_AMOUNT></APPLIED_AMOUNT>
      <RECEIPT_AMOUNT>36059.14</RECEIPT_AMOUNT>
      <RECEIPT_DATE>11-JUL-17</RECEIPT_DATE>
      <STATUS>Unapplied</STATUS>
    </G_RECEIPT_NUMBER>
  </LIST_G_RECEIPT_NUMBER>
</IPC_RPT_2166>
