<?xml version="1.0" encoding="WINDOWS-1252"?>
<!-- Generated by Oracle Reports version 10.1.2.0.2 -->
<IPC_RPT_2138>
  <LIST_G_DOC_SEQUENCE_VALUE>
    <G_DOC_SEQUENCE_VALUE>
      <DOC_SEQUENCE_VALUE>70100009021</DOC_SEQUENCE_VALUE>
      <VOUCHER_NO></VOUCHER_NO>
      <ACCOUNTING_DATE>31-JUL-17</ACCOUNTING_DATE>
      <LIST_G_ACCOUNT_NO>
        <G_ACCOUNT_NO>
          <ACCOUNTED_CR></ACCOUNTED_CR>
          <ACCOUNTED_DR>9121829.49</ACCOUNTED_DR>
          <ACCOUNT_NO>61114</ACCOUNT_NO>
          <ACCOUNT_NAME>BANK OF TOKYO MITSUBISHI HEAD OFFICE/YEN ACCOUNT</ACCOUNT_NAME>
          <COST_CENTER>-</COST_CENTER>
          <EMPLOYEE>-</EMPLOYEE>
          <MODEL>-</MODEL>
          <BUDGET_ACOUNT>-</BUDGET_ACOUNT>
          <BUDGET_COST_CENTER>-</BUDGET_COST_CENTER>
          <REFERENCE>0731108</REFERENCE>
          <DESCRIPTION></DESCRIPTION>
        </G_ACCOUNT_NO>
        <G_ACCOUNT_NO>
          <ACCOUNTED_CR>157621.49</ACCOUNTED_CR>
          <ACCOUNTED_DR></ACCOUNTED_DR>
          <ACCOUNT_NO>41600</ACCOUNT_NO>
          <ACCOUNT_NAME>Foreign exchange gain</ACCOUNT_NAME>
          <COST_CENTER>-</COST_CENTER>
          <EMPLOYEE>-</EMPLOYEE>
          <MODEL>-</MODEL>
          <BUDGET_ACOUNT>-</BUDGET_ACOUNT>
          <BUDGET_COST_CENTER>-</BUDGET_COST_CENTER>
          <REFERENCE>0731108</REFERENCE>
          <DESCRIPTION>Receipt Application to Transaction Type - Debit Memo /Transaction Number 50100000040 /Transaction Document Number 50100000040 /Constant</DESCRIPTION>
        </G_ACCOUNT_NO>
        <G_ACCOUNT_NO>
          <ACCOUNTED_CR>8964208</ACCOUNTED_CR>
          <ACCOUNTED_DR></ACCOUNTED_DR>
          <ACCOUNT_NO>66904</ACCOUNT_NO>
          <ACCOUNT_NAME>Accounts receivable - non trade</ACCOUNT_NAME>
          <COST_CENTER>-</COST_CENTER>
          <EMPLOYEE>-</EMPLOYEE>
          <MODEL>-</MODEL>
          <BUDGET_ACOUNT>-</BUDGET_ACOUNT>
          <BUDGET_COST_CENTER>-</BUDGET_COST_CENTER>
          <REFERENCE>0731108</REFERENCE>
          <DESCRIPTION>Receipt Application to Transaction Type - Debit Memo  Transaction Number 50100000040  Transaction Document Number 50100000040</DESCRIPTION>
        </G_ACCOUNT_NO>
        <G_ACCOUNT_NO>
          <ACCOUNTED_CR></ACCOUNTED_CR>
          <ACCOUNTED_DR>8964208</ACCOUNTED_DR>
          <ACCOUNT_NO>61000</ACCOUNT_NO>
          <ACCOUNT_NAME>Interim Cash account</ACCOUNT_NAME>
          <COST_CENTER>-</COST_CENTER>
          <EMPLOYEE>-</EMPLOYEE>
          <MODEL>-</MODEL>
          <BUDGET_ACOUNT>-</BUDGET_ACOUNT>
          <BUDGET_COST_CENTER>-</BUDGET_COST_CENTER>
          <REFERENCE>0731108</REFERENCE>
          <DESCRIPTION>Currency Balancing Line</DESCRIPTION>
        </G_ACCOUNT_NO>
        <G_ACCOUNT_NO>
          <ACCOUNTED_CR>9121829.49</ACCOUNTED_CR>
          <ACCOUNTED_DR></ACCOUNTED_DR>
          <ACCOUNT_NO>84303</ACCOUNT_NO>
          <ACCOUNT_NAME>Advances received from customers</ACCOUNT_NAME>
          <COST_CENTER>-</COST_CENTER>
          <EMPLOYEE>-</EMPLOYEE>
          <MODEL>-</MODEL>
          <BUDGET_ACOUNT>-</BUDGET_ACOUNT>
          <BUDGET_COST_CENTER>-</BUDGET_COST_CENTER>
          <REFERENCE>0731108</REFERENCE>
          <DESCRIPTION></DESCRIPTION>
        </G_ACCOUNT_NO>
        <G_ACCOUNT_NO>
          <ACCOUNTED_CR>18243658.98</ACCOUNTED_CR>
          <ACCOUNTED_DR></ACCOUNTED_DR>
          <ACCOUNT_NO>61000</ACCOUNT_NO>
          <ACCOUNT_NAME>Interim Cash account</ACCOUNT_NAME>
          <COST_CENTER>-</COST_CENTER>
          <EMPLOYEE>-</EMPLOYEE>
          <MODEL>-</MODEL>
          <BUDGET_ACOUNT>-</BUDGET_ACOUNT>
          <BUDGET_COST_CENTER>-</BUDGET_COST_CENTER>
          <REFERENCE>0731108</REFERENCE>
          <DESCRIPTION>Currency Balancing Line</DESCRIPTION>
        </G_ACCOUNT_NO>
        <G_ACCOUNT_NO>
          <ACCOUNTED_CR></ACCOUNTED_CR>
          <ACCOUNTED_DR>9279450.98</ACCOUNTED_DR>
          <ACCOUNT_NO>61000</ACCOUNT_NO>
          <ACCOUNT_NAME>Interim Cash account</ACCOUNT_NAME>
          <COST_CENTER>-</COST_CENTER>
          <EMPLOYEE>-</EMPLOYEE>
          <MODEL>-</MODEL>
          <BUDGET_ACOUNT>-</BUDGET_ACOUNT>
          <BUDGET_COST_CENTER>-</BUDGET_COST_CENTER>
          <REFERENCE>0731108</REFERENCE>
          <DESCRIPTION>Currency Balancing Line</DESCRIPTION>
        </G_ACCOUNT_NO>
        <G_ACCOUNT_NO>
          <ACCOUNTED_CR></ACCOUNTED_CR>
          <ACCOUNTED_DR>9121829.49</ACCOUNTED_DR>
          <ACCOUNT_NO>84303</ACCOUNT_NO>
          <ACCOUNT_NAME>Advances received from customers</ACCOUNT_NAME>
          <COST_CENTER>-</COST_CENTER>
          <EMPLOYEE>-</EMPLOYEE>
          <MODEL>-</MODEL>
          <BUDGET_ACOUNT>-</BUDGET_ACOUNT>
          <BUDGET_COST_CENTER>-</BUDGET_COST_CENTER>
          <REFERENCE>0731108</REFERENCE>
          <DESCRIPTION>Receipt Application to Transaction Type - Debit Memo /Transaction Number 50100000040 /Transaction Document Number 50100000040 /Constant</DESCRIPTION>
        </G_ACCOUNT_NO>
      </LIST_G_ACCOUNT_NO>
    </G_DOC_SEQUENCE_VALUE>
  </LIST_G_DOC_SEQUENCE_VALUE>
  <CF_PRINTED_BY></CF_PRINTED_BY>
  <CF_CHECKED_BY></CF_CHECKED_BY>
  <CF_NOTED_BY></CF_NOTED_BY>
</IPC_RPT_2138>
